odoo/addons/stock_picking_restrict_cancel_printed/README.rst
odoo/addons/stock_picking_restrict_cancel_printed/__init__.py
odoo/addons/stock_picking_restrict_cancel_printed/__manifest__.py
odoo/addons/stock_picking_restrict_cancel_printed/i18n/it.po
odoo/addons/stock_picking_restrict_cancel_printed/i18n/stock_picking_restrict_cancel_printed.pot
odoo/addons/stock_picking_restrict_cancel_printed/models/__init__.py
odoo/addons/stock_picking_restrict_cancel_printed/models/stock_move.py
odoo/addons/stock_picking_restrict_cancel_printed/models/stock_picking.py
odoo/addons/stock_picking_restrict_cancel_printed/models/stock_picking_type.py
odoo/addons/stock_picking_restrict_cancel_printed/readme/CONTRIBUTORS.rst
odoo/addons/stock_picking_restrict_cancel_printed/readme/DESCRIPTION.rst
odoo/addons/stock_picking_restrict_cancel_printed/static/description/icon.png
odoo/addons/stock_picking_restrict_cancel_printed/static/description/index.html
odoo/addons/stock_picking_restrict_cancel_printed/tests/__init__.py
odoo/addons/stock_picking_restrict_cancel_printed/tests/test_stock_picking_restrict_cancel_printed.py
odoo/addons/stock_picking_restrict_cancel_printed/views/stock_picking_type_views.xml
odoo/addons/stock_picking_restrict_cancel_printed/views/stock_picking_views.xml
odoo14_addon_stock_picking_restrict_cancel_printed-14.0.1.1.2.dist-info/METADATA
odoo14_addon_stock_picking_restrict_cancel_printed-14.0.1.1.2.dist-info/WHEEL
odoo14_addon_stock_picking_restrict_cancel_printed-14.0.1.1.2.dist-info/top_level.txt
odoo14_addon_stock_picking_restrict_cancel_printed-14.0.1.1.2.dist-info/RECORD
