Metadata-Version: 2.1
Name: odoo14-addon-stock_picking_restrict_cancel_printed
Version: 14.0.1.1.2
Summary: Prevent canceling a stock transfer if printed.
Home-page: https://github.com/OCA/stock-logistics-workflow
Author: Camptocamp, BCIM, Odoo Community Association (OCA)
Author-email: support@odoo-community.org
License: AGPL-3
Classifier: Programming Language :: Python
Classifier: Framework :: Odoo
Classifier: Framework :: Odoo :: 14.0
Classifier: License :: OSI Approved :: GNU Affero General Public License v3
Classifier: Development Status :: 4 - Beta
Requires-Python: >=3.6
Requires-Dist: odoo<14.1dev,>=14.0a
